[
    {
        "data": {
            "node": {
                "__typename": "User",
                "id": "pfbid0AWQNEZEr3HdCkuapv5zgi3b9XRtSpXXtAtvGpnaCAFBpEJPjUCcYFgjN2WZsYUpzl",
                "timeline_list_feed_units": {
                    "edges": []
                }
            }
        },
        "extensions": {
            "is_final": false
        }
    },
    {
        "label": "ProfileCometTimelineFeed_user$defer$ProfileCometTimelineFeed_user_timeline_list_feed_units$page_info",
        "path": [
            "node",
            "timeline_list_feed_units"
        ],
        "data": {
            "page_info": {
                "has_next_page": false,
                "end_cursor": null
            }
        },
        "extensions": {
            "is_final": true
        }
    }
]